README.rst
setup.cfg
setup.py
biothings_explorer_test/__init__.py
biothings_explorer_test.egg-info/PKG-INFO
biothings_explorer_test.egg-info/SOURCES.txt
biothings_explorer_test.egg-info/dependency_links.txt
biothings_explorer_test.egg-info/requires.txt
biothings_explorer_test.egg-info/top_level.txt